parecord_wrapper/__init__.py
parecord_wrapper/parecord.py
paudio_wrapper-0.1.1.dist-info/LICENSE
paudio_wrapper-0.1.1.dist-info/METADATA
paudio_wrapper-0.1.1.dist-info/WHEEL
paudio_wrapper-0.1.1.dist-info/top_level.txt
paudio_wrapper-0.1.1.dist-info/RECORD
