Metadata-Version: 2.1
Name: paudio-wrapper
Version: 0.1.1
Summary: A Python wrapper for paplay and parecord to play and record audio using PulseAudio.
Home-page: https://github.com/yourusername/parecord-wrapper
Author: afrhan-repo
Author-email: afrhanhossain11@gmail.com
Classifier: Programming Language :: Python :: 3
Classifier: License :: OSI Approved :: MIT License
Classifier: Operating System :: OS Independent
Requires-Python: >=3.6
License-File: LICENSE
